Workbook

Sheet README
A1: Cookychoice - Keyword Research (cookychoice.com)
A2: Business: Rice selling website, Dubai. Target: whole UAE. Goal: organic rankings + product orders.
A4: STATUS OF DATA
A5: Keyword universe, clusters, intent, location, and page mapping are filled (built from product knowledge, NOT from a live tool).
A6: Search Volume, KD, CPC, Competition columns are EMPTY on purpose. No numbers have been invented. Fill them from Semrush / Keyword Planner export (see steps below).
A7: Priority score and Priority tier compute automatically once Volume and KD are filled.
A9: HOW TO FILL VOLUME / KD
A10: 1. Semrush -> Keyword Magic Tool -> database: United Arab Emirates -> seed (e.g. basmati rice) -> Export CSV.
A11: 2. Semrush -> Keyword Overview -> Bulk Analysis: paste the 'Keyword' column from Keyword Master -> export (gives Volume, KD%, CPC).
A12: 3. Google Keyword Planner -> Get search volume and forecasts -> paste keywords -> location United Arab Emirates (also Dubai) -> download.
A13: 4. Paste exports in tabs 'Semrush Import' and 'KP Import', then Keyword Master columns I-L pull values via VLOOKUP automatically.
A15: TABS
... A22: Audit Checklist - technical and on-page items to verify on the site

Sheet Keyword Master
A1: Keyword | B1: Cluster / Term group | C1: Product category | D1: Search intent | E1: Funnel stage | F1: Location | G1: Target page (suggested) | H1: Page type | I1: Search Volume (Semrush) | J1: KD % (Semrush) | K1: CPC USD | L1: KP Avg Monthly Searches | M1: Priority score | N1: Priority tier | O1: Status | P1: Notes
A2: basmati rice | B2: Core product | C2: Basmati | D2: Informational/Commercial | E2: TOFU | F2: UAE (generic) | G2: Basmati Rice category | H2: Category | I2: =IFERROR(VLOOKUP($A2,'Semrush Import'!$A:$D,2,FALSE),"") | J2: =IFERROR(VLOOKUP($A2,'Semrush Import'!$A:$D,3,FALSE),"") | K2: =IFERROR(VLOOKUP($A2,'Semrush Import'!$A:$D,4,FALSE),"") | L2: =IFERROR(VLOOKUP($A2,'KP Import'!$A:$B,2,FALSE),"") | M2: =IF(I2="","",ROUND(I2/(J2+10),1)) | N2: =IF(M2="","",IF(M2>=20,"A - Go first",IF(M2>=5,"B - Next","C - Later"))) | O2: To research
A3: buy basmati rice online | B3: Transactional | C3: Basmati | D3: Transactional | E3: BOFU | F3: UAE (generic) | G3: Basmati Rice category | H3: Category | I3: =IFERROR(VLOOKUP($A3,'Semrush Import'!$A:$D,2,FALSE),"") | J3: =IFERROR(VLOOKUP($A3,'Semrush Import'!$A:$D,3,FALSE),"") | K3: =IFERROR(VLOOKUP($A3,'Semrush Import'!$A:$D,4,FALSE),"") | L3: =IFERROR(VLOOKUP($A3,'KP Import'!$A:$B,2,FALSE),"") | M3: =IF(I3="","",ROUND(I3/(J3+10),1)) | N3: =IF(M3="","",IF(M3>=20,"A - Go first",IF(M3>=5,"B - Next","C - Later"))) | O3: To research
A4: basmati rice price in uae | B4: Price | C4: Basmati | D4: Commercial/Transactional | E4: MOFU | F4: UAE | G4: Basmati Rice category | H4: Category | I4: =IFERROR(VLOOKUP($A4,'Semrush Import'!$A:$D,2,FALSE),"") | J4: =IFERROR(VLOOKUP($A4,'Semrush Import'!$A:$D,3,FALSE),"") | K4: =IFERROR(VLOOKUP($A4,'Semrush Import'!$A:$D,4,FALSE),"") | L4: =IFERROR(VLOOKUP($A4,'KP Import'!$A:$B,2,FALSE),"") | M4: =IF(I4="","",ROUND(I4/(J4+10),1)) | N4: =IF(M4="","",IF(M4>=20,"A - Go first",IF(M4>=5,"B - Next","C - Later"))) | O4: To research
A5: basmati rice price in dubai | B5: Price | C5: Basmati | D5: Commercial/Transactional | E5: MOFU | F5: Dubai | G5: Basmati Rice category | H5: Category | I5: =IFERROR(VLOOKUP($A5,'Semrush Import'!$A:$D,2,FALSE),"") | J5: =IFERROR(VLOOKUP($A5,'Semrush Import'!$A:$D,3,FALSE),"") | K5: =IFERROR(VLOOKUP($A5,'Semrush Import'!$A:$D,4,FALSE),"") | L5: =IFERROR(VLOOKUP($A5,'KP Import'!$A:$B,2,FALSE),"") | M5: =IF(I5="","",ROUND(I5/(J5+10),1)) | N5: =IF(M5="","",IF(M5>=20,"A - Go first",IF(M5>=5,"B - Next","C - Later"))) | O5: To research
A6: basmati rice online dubai | B6: Transactional | C6: Basmati | D6: Transactional | E6: BOFU | F6: Dubai | G6: Basmati Rice category | H6: Category | I6: =IFERROR(VLOOKUP($A6,'Semrush Import'!$A:$D,2,FALSE),"") | J6: =IFERROR(VLOOKUP($A6,'Semrush Import'!$A:$D,3,FALSE),"") | K6: =IFERROR(VLOOKUP($A6,'Semrush Import'!$A:$D,4,FALSE),"") | L6: =IFERROR(VLOOKUP($A6,'KP Import'!$A:$B,2,FALSE),"") | M6: =IF(I6="","",ROUND(I6/(J6+10),1)) | N6: =IF(M6="","",IF(M6>=20,"A - Go first",IF(M6>=5,"B - Next","C - Later"))) | O6: To research
A7: basmati rice wholesale dubai | B7: Wholesale/B2B | C7: Basmati | D7: Transactional (B2B) | E7: BOFU | F7: Dubai | G7: Wholesale landing page | H7: Landing | I7: =IFERROR(VLOOKUP($A7,'Semrush Import'!$A:$D,2,FALSE),"") | J7: =IFERROR(VLOOKUP($A7,'Semrush Import'!$A:$D,3,FALSE),"") | K7: =IFERROR(VLOOKUP($A7,'Semrush Import'!$A:$D,4,FALSE),"") | L7: =IFERROR(VLOOKUP($A7,'KP Import'!$A:$B,2,FALSE),"") | M7: =IF(I7="","",ROUND(I7/(J7+10),1)) | N7: =IF(M7="","",IF(M7>=20,"A - Go first",IF(M7>=5,"B - Next","C - Later"))) | O7: To research
A8: basmati rice supplier uae | B8: Wholesale/B2B | C8: Basmati | D8: Transactional (B2B) | E8: BOFU | F8: UAE | G8: Wholesale landing page | H8: Landing | I8: =IFERROR(VLOOKUP($A8,'Semrush Import'!$A:$D,2,FALSE),"") | J8: =IFERROR(VLOOKUP($A8,'Semrush Import'!$A:$D,3,FALSE),"") | K8: =IFERROR(VLOOKUP($A8,'Semrush Import'!$A:$D,4,FALSE),"") | L8: =IFERROR(VLOOKUP($A8,'KP Import'!$A:$B,2,FALSE),"") | M8: =IF(I8="","",ROUND(I8/(J8+10),1)) | N8: =IF(M8="","",IF(M8>=20,"A - Go first",IF(M8>=5,"B - Next","C - Later"))) | O8: To research
A9: 1121 basmati rice | B9: Core product | C9: Basmati | D9: Informational/Commercial | E9: TOFU | F9: UAE (generic) | G9: 1121 Basmati product page | H9: Product | I9: =IFERROR(VLOOKUP($A9,'Semrush Import'!$A:$D,2,FALSE),"") | J9: =IFERROR(VLOOKUP($A9,'Semrush Import'!$A:$D,3,FALSE),"") | K9: =IFERROR(VLOOKUP($A9,'Semrush Import'!$A:$D,4,FALSE),"") | L9: =IFERROR(VLOOKUP($A9,'KP Import'!$A:$B,2,FALSE),"") | M9: =IF(I9="","",ROUND(I9/(J9+10),1)) | N9: =IF(M9="","",IF(M9>=20,"A - Go first",IF(M9>=5,"B - Next","C - Later"))) | O9: To research
A10: buy 1121 basmati rice online | B10: Transactional | C10: Basmati | D10: Transactional | E10: BOFU | F10: UAE (generic) | G10: 1121 Basmati product page | H10: Product | I10: =IFERROR(VLOOKUP($A10,'Semrush Import'!$A:$D,2,FALSE),"") | J10: =IFERROR(VLOOKUP($A10,'Semrush Import'!$A:$D,3,FALSE),"") | K10: =IFERROR(VLOOKUP($A10,'Semrush Import'!$A:$D,4,FALSE),"") | L10: =IFERROR(VLOOKUP($A10,'KP Import'!$A:$B,2,FALSE),"") | M10: =IF(I10="","",ROUND(I10/(J10+10),1)) | N10: =IF(M10="","",IF(M10>=20,"A - Go first",IF(M10>=5,"B - Next","C - Later"))) | O10: To research
A11: 1121 basmati rice price in uae | B11: Price | C11: Basmati | D11: Commercial/Transactional | E11: MOFU | F11: UAE | G11: 1121 Basmati product page | H11: Product | I11: =IFERROR(VLOOKUP($A11,'Semrush Import'!$A:$D,2,FALSE),"") | J11: =IFERROR(VLOOKUP($A11,'Semrush Import'!$A:$D,3,FALSE),"") | K11: =IFERROR(VLOOKUP($A11,'Semrush Import'!$A:$D,4,FALSE),"") | L11: =IFERROR(VLOOKUP($A11,'KP Import'!$A:$B,2,FALSE),"") | M11: =IF(I11="","",ROUND(I11/(J11+10),1)) | N11: =IF(M11="","",IF(M11>=20,"A - Go first",IF(M11>=5,"B - Next","C - Later"))) | O11: To research
A12: 1121 basmati rice price in dubai | B12: Price | C12: Basmati | D12: Commercial/Transactional | E12: MOFU | F12: Dubai | G12: 1121 Basmati product page | H12: Product | I12: =IFERROR(VLOOKUP($A12,'Semrush Import'!$A:$D,2,FALSE),"") | J12: =IFERROR(VLOOKUP($A12,'Semrush Import'!$A:$D,3,FALSE),"") | K12: =IFERROR(VLOOKUP($A12,'Semrush Import'!$A:$D,4,FALSE),"") | L12: =IFERROR(VLOOKUP($A12,'KP Import'!$A:$B,2,FALSE),"") | M12: =IF(I12="","",ROUND(I12/(J12+10),1)) | N12: =IF(M12="","",IF(M12>=20,"A - Go first",IF(M12>=5,"B - Next","C - Later"))) | O12: To research
A13: 1121 basmati rice online dubai | B13: Transactional | C13: Basmati | D13: Transactional | E13: BOFU | F13: Dubai | G13: 1121 Basmati product page | H13: Product | I13: =IFERROR(VLOOKUP($A13,'Semrush Import'!$A:$D,2,FALSE),"") | J13: =IFERROR(VLOOKUP($A13,'Semrush Import'!$A:$D,3,FALSE),"") | K13: =IFERROR(VLOOKUP($A13,'Semrush Import'!$A:$D,4,FALSE),"") | L13: =IFERROR(VLOOKUP($A13,'KP Import'!$A:$B,2,FALSE),"") | M13: =IF(I13="","",ROUND(I13/(J13+10),1)) | N13: =IF(M13="","",IF(M13>=20,"A - Go first",IF(M13>=5,"B - Next","C - Later"))) | O13: To research
... A494: ارز كبسة | B494: Arabic | C494: Arabic | D494: Transactional | E494: BOFU | F494: UAE (Arabic) | G494: Arabic version pages (/ar/) | H494: Arabic landing | I494: =IFERROR(VLOOKUP($A494,'Semrush Import'!$A:$D,2,FALSE),"") | J494: =IFERROR(VLOOKUP($A494,'Semrush Import'!$A:$D,3,FALSE),"") | K494: =IFERROR(VLOOKUP($A494,'Semrush Import'!$A:$D,4,FALSE),"") | L494: =IFERROR(VLOOKUP($A494,'KP Import'!$A:$B,2,FALSE),"") | M494: =IF(I494="","",ROUND(I494/(J494+10),1)) | N494: =IF(M494="","",IF(M494>=20,"A - Go first",IF(M494>=5,"B - Next","C - Later"))) | O494: To research

Sheet Semrush Import
A1: Keyword | B1: Search Volume | C1: Keyword Difficulty (KD %) | D1: CPC (USD) | E1: Competition | F1: Intent (Semrush)

Sheet KP Import
A1: Keyword | B1: Avg Monthly Searches | C1: Competition | D1: Top of page bid (low) | E1: Top of page bid (high)

Sheet Location Wise
A1: Location | B1: Level | C1: Suggested page | D1: Keywords to target | E1: Likely priority (judgement, verify with volume) | F1: Notes
A2: Dubai | B2: Emirate | C2: /dubai-rice-delivery/ (suggested) | D2: rice delivery dubai; basmati rice dubai; rice wholesale dubai; rice supplier dubai | E2: High | F2: Own landing page with delivery info, local FAQ, LocalBusiness/Service schema
A3: Abu Dhabi | B3: Emirate | C3: /abu-dhabi-rice-delivery/ (suggested) | D3: rice delivery abu dhabi; basmati rice abu dhabi; rice wholesale abu dhabi; rice supplier abu dhabi | E3: High | F3: Own landing page with delivery info, local FAQ, LocalBusiness/Service schema
A4: Sharjah | B4: Emirate | C4: /sharjah-rice-delivery/ (suggested) | D4: rice delivery sharjah; basmati rice sharjah; rice wholesale sharjah; rice supplier sharjah | E4: High | F4: Own landing page with delivery info, local FAQ, LocalBusiness/Service schema
A5: Ajman | B5: Emirate | C5: /ajman-rice-delivery/ (suggested) | D5: rice delivery ajman; basmati rice ajman; rice wholesale ajman; rice supplier ajman | E5: Medium | F5: Own landing page with delivery info, local FAQ, LocalBusiness/Service schema
A6: Ras Al Khaimah | B6: Emirate | C6: /ras-al-khaimah-rice-delivery/ (suggested) | D6: rice delivery ras al khaimah; basmati rice ras al khaimah; rice wholesale ras al khaimah; rice supplier ras al khaimah | E6: Medium | F6: Own landing page with delivery info, local FAQ, LocalBusiness/Service schema
A7: Fujairah | B7: Emirate | C7: /fujairah-rice-delivery/ (suggested) | D7: rice delivery fujairah; basmati rice fujairah; rice wholesale fujairah; rice supplier fujairah | E7: Medium | F7: Own landing page with delivery info, local FAQ, LocalBusiness/Service schema
A8: Umm Al Quwain | B8: Emirate | C8: /umm-al-quwain-rice-delivery/ (suggested) | D8: rice delivery umm al quwain; basmati rice umm al quwain; rice wholesale umm al quwain; rice supplier umm al quwain | E8: Medium | F8: Own landing page with delivery info, local FAQ, LocalBusiness/Service schema
A9: Al Ain | B9: Emirate | C9: /al-ain-rice-delivery/ (suggested) | D9: rice delivery al ain; basmati rice al ain; rice wholesale al ain; rice supplier al ain | E9: Medium | F9: Own landing page with delivery info, local FAQ, LocalBusiness/Service schema
A10: Dubai - Deira | B10: Area | C10: Section on Dubai page (or own page if volume proves) | D10: rice delivery deira; rice wholesale deira | E10: Medium | F10: Add to 'areas we deliver' block; create page only if Semrush shows volume
A11: Dubai - Bur Dubai | B11: Area | C11: Section on Dubai page (or own page if volume proves) | D11: rice delivery bur dubai; rice wholesale bur dubai | E11: Low | F11: Add to 'areas we deliver' block; create page only if Semrush shows volume
A12: Dubai - Al Quoz | B12: Area | C12: Section on Dubai page (or own page if volume proves) | D12: rice delivery al quoz; rice wholesale al quoz | E12: Medium | F12: Add to 'areas we deliver' block; create page only if Semrush shows volume
... A31: Sharjah - Muwaileh | B31: Area | C31: Section on Sharjah page | D31: rice wholesale muwaileh sharjah | E31: Low | F31: Include in Sharjah page

Sheet Page Mapping
A1: Page | B1: Suggested URL | C1: Primary keyword | D1: Secondary keywords | E1: Suggested title tag (<=60 chars check) | F1: Suggested H1
A2: Home | B2: / | C2: buy rice online uae | D2: rice delivery dubai; rice online dubai; basmati rice uae; rice wholesale uae | E2: Buy Rice Online in UAE | Basmati & Wholesale Rice Delivery Dubai | F2: Premium Rice Delivered Across Dubai & UAE
A3: Basmati Rice (category) | B3: /basmati-rice/ | C3: basmati rice dubai | D3: buy basmati rice online; basmati rice price in uae; best basmati rice in uae; aged basmati | E3: Basmati Rice Online Dubai - Price, Brands & Delivery | F3: Basmati Rice in Dubai
A4: 1121 Basmati (product/sub-cat) | B4: /basmati-rice/1121/ | C4: 1121 basmati rice | D4: 1121 basmati rice price in uae; extra long grain basmati | E4: 1121 Basmati Rice UAE - Buy Online 5kg/10kg/20kg | F4: 1121 Basmati Rice
A5: Sella Basmati | B5: /basmati-rice/sella/ | C5: sella basmati rice | D5: golden sella basmati rice; white sella basmati rice; sella basmati price in uae | E5: Sella Basmati Rice UAE - Golden & White Sella | F5: Sella Basmati Rice
A6: Steam Basmati | B6: /basmati-rice/steam/ | C6: steam basmati rice | D6: steam basmati rice price in uae | E6: Steam Basmati Rice UAE - Buy Online | F6: Steam Basmati Rice
A7: Non-Basmati (category) | B7: /non-basmati-rice/ | C7: parboiled rice | D7: raw rice; long grain white rice; medium grain rice | E7: Non-Basmati Rice UAE - Parboiled, Raw, Long Grain | F7: Non-Basmati Rice
A8: South Indian Rice | B8: /south-indian-rice/ | C8: sona masoori rice | D8: ponni rice; matta rice; kerala matta rice; idli rice | E8: South Indian Rice UAE - Sona Masoori, Matta, Ponni | F8: South Indian Rice in UAE
A9: Specialty / Healthy Rice | B9: /specialty-rice/ | C9: jasmine rice | D9: sushi rice; arborio rice; brown rice; red rice; black rice; wild rice | E9: Jasmine, Brown & Specialty Rice UAE | F9: Specialty & Healthy Rice
A10: Wholesale / Bulk (B2B) | B10: /rice-wholesale-dubai/ | C10: rice wholesale dubai | D10: bulk rice dubai; rice supplier uae; rice distributor dubai; rice for restaurants dubai; 25kg/50kg | E10: Rice Wholesale Dubai - Bulk Rice Supplier UAE | F10: Bulk Rice Supplier in Dubai & UAE
A11: Delivery page | B11: /rice-delivery-dubai/ | C11: rice delivery dubai | D11: same day rice delivery dubai; rice home delivery uae; cash on delivery rice | E11: Rice Delivery Dubai - Same Day Home Delivery | F11: Rice Delivery in Dubai
A12: Biryani Rice | B12: /biryani-rice/ | C12: biryani rice | D12: rice for biryani; best rice for biryani in dubai | E12: Best Rice for Biryani in Dubai & UAE | F12: Biryani Rice
... A19: Arabic version | B19: /ar/ | C19: ارز بسمتي دبي | D19: ارز بسمتي بالجملة; سعر الارز في الامارات; توصيل ارز دبي | E19: ارز بسمتي دبي - توصيل ارز في الامارات | F19: ارز بسمتي في دبي

Sheet Questions & Blog
A1: Keyword / question | B1: Type | C1: Intent | D1: Suggested article title | E1: Internal link to | F1: Search Volume | G1: KD %
A2: how to cook basmati rice | B2: Cooking guide | C2: Informational | D2: How to cook basmati rice (UAE guide) | E2: Relevant category / product page
A3: basmati rice vs jasmine rice | B3: Comparison | C3: Informational | D3: Basmati rice vs jasmine rice (UAE guide) | E3: Relevant category / product page
A4: 1121 basmati vs sella basmati | B4: Comparison | C4: Informational | D4: 1121 basmati vs sella basmati (UAE guide) | E4: Relevant category / product page
A5: difference between sella and steam basmati | B5: Comparison | C5: Informational | D5: Difference between sella and steam basmati (UAE guide) | E5: Relevant category / product page
A6: how to identify real basmati rice | B6: Buying guide | C6: Informational | D6: How to identify real basmati rice (UAE guide) | E6: Relevant category / product page
A7: how to choose basmati rice | B7: Buying guide | C7: Informational | D7: How to choose basmati rice (UAE guide) | E7: Relevant category / product page
A8: how to store rice long term | B8: Storage | C8: Informational | D8: How to store rice long term (UAE guide) | E8: Relevant category / product page
A9: how long does basmati rice last | B9: Storage | C9: Informational | D9: How long does basmati rice last (UAE guide) | E9: Relevant category / product page
A10: rice to water ratio for biryani | B10: Cooking guide | C10: Informational | D10: Rice to water ratio for biryani (UAE guide) | E10: Relevant category / product page
A11: how to cook rice for kabsa | B11: Cooking guide | C11: Informational | D11: How to cook rice for kabsa (UAE guide) | E11: Relevant category / product page
A12: how to make chicken mandi rice | B12: Recipe | C12: Informational | D12: How to make chicken mandi rice (UAE guide) | E12: Relevant category / product page
A13: how to make dubai style biryani | B13: Recipe | C13: Informational | D13: How to make dubai style biryani (UAE guide) | E13: Relevant category / product page
... A31: rice trading license dubai | B31: B2B guide | C31: Informational | D31: Rice trading license dubai (UAE guide) | E31: Relevant category / product page

Sheet Competitor Research
A1: Step | B1: What to do in Semrush | C1: Output to paste/summarise
A2: 1 | B2: Google 'basmati rice online dubai', 'rice wholesale dubai', 'rice delivery uae' and note top 10 domains (UAE results) | C2: Competitor domain list
A3: 2 | B3: Semrush -> Domain Overview for each domain (UAE database) | C3: Organic traffic, keywords count, authority score
A4: 3 | B4: Keyword Gap: cookychoice.com vs 3-5 competitors | C4: Missing / weak / shared keywords
A5: 4 | B5: Organic Research -> Pages for each competitor | C5: Top traffic pages = page types to copy
A6: 5 | B6: Backlink Gap | C6: Link targets (UAE directories, food blogs, B2B listings)
A7: 6 | B7: Note SERP features: Shopping, Local pack, PAA | C7: Where to add schema / Google Business Profile

Sheet Audit Checklist
A1: Area | B1: Check | C1: Severity | D1: Status
A2: Indexing | B2: WordPress Settings > Reading > 'Discourage search engines' must be OFF | C2: Critical | D2: Reported by owner as ON; confirm removed
A3: Indexing | B3: robots.txt has no 'Disallow: /' | C3: Critical | D3: Not yet verified (site not reachable from session)
A4: Indexing | B4: No noindex meta / X-Robots-Tag on pages | C4: Critical | D4: Not yet verified
A5: Indexing | B5: XML sitemap submitted in Search Console | C5: High | D5: Not yet verified
A6: On-page | B6: Unique title (<=60) & meta description (<=155) per page, keyword in title | C6: High | D6: Not yet verified
A7: On-page | B7: One H1 per page with primary keyword | C7: High | D7: Not yet verified
A8: On-page | B8: Product pages: unique descriptions, pack sizes, price in AED, FAQ | C8: High | D8: Not yet verified
A9: Schema | B9: Product, Offer (AED), Organization, LocalBusiness, FAQPage, BreadcrumbList | C9: High | D9: Not yet verified
A10: Local | B10: Google Business Profile + UAE citations (NAP consistent) | C10: High | D10: Not yet verified
A11: Technical | B11: HTTPS, www/non-www redirect, canonical tags, no duplicate URLs | C11: High | D11: Not yet verified
A12: Technical | B12: Core Web Vitals / mobile speed, image compression, WebP | C12: Medium | D12: Not yet verified
... A14: Content | B14: Blog hub and internal linking from guides to category pages | C14: Medium | D14: Not yet verified
